[{"place_id": "638315", "licence": "Data \u00a9 OpenStreetMap contributors, ODbL 1.0. http://www.openstreetmap.org/copyright", "osm_type": "node", "osm_id": "244080892", "boundingbox": ["43.6757587", "43.9957587", "126.3834936", "126.7034936"], "lat": "43.8357587", "lon": "126.5434936", "display_name": "\u5409\u6797\u5e02, \u8239\u8425\u533a / Chuanying, \u5409\u6797\u5e02 / Jilin, \u5409\u6797\u7701, 132011, \u4e2d\u56fd", "class": "place", "type": "city", "importance": 0.31089087672135, "icon": "https://nominatim.openstreetmap.org/images/mapicons/poi_place_city.p.20.png", "geojson": {"type": "Point", "coordinates": [126.5434936, 43.8357587]}}]